<?xml version="1.0" encoding="utf-8"?>
<Elements xmlns="http://schemas.microsoft.com/sharepoint/">
  <ListInstance Title="Customers"
                OnQuickLaunch="TRUE"
                TemplateType="105"
                FeatureId="00bfea71-7e6d-4186-9ba8-c047ac750105"
                Url="Lists/Customers"
                Description="List of sample customer data">
    <Data>
      <Rows>
        <Row>
          <Field Name="FirstName">Scot</Field>
          <Field Name="Title">Hillier</Field>
          <Field Name="WorkPhone">(123)456-6789</Field>
        </Row>
        <Row>
          <Field Name="FirstName">Andrew</Field>
          <Field Name="Title">Connell</Field>
          <Field Name="WorkPhone">(987)654-3210</Field>
        </Row>
        <Row>
          <Field Name="FirstName">Steve</Field>
          <Field Name="Title">Fox</Field>
          <Field Name="WorkPhone">(800)LUV-AZUR</Field>
        </Row>
        <Row>
          <Field Name="FirstName">Donovan</Field>
          <Field Name="Title">Follette</Field>
          <Field Name="WorkPhone">(888)123-5677</Field>
        </Row>
        <Row>
          <Field Name="FirstName">Rob</Field>
          <Field Name="Title">Howard</Field>
          <Field Name="WorkPhone">(800)U4O-AUTH</Field>
        </Row>
        <Row>
          <Field Name="FirstName">Paul</Field>
          <Field Name="Title">Stubbs</Field>
          <Field Name="WorkPhone">(543)675-7654</Field>
        </Row>
        <Row>
          <Field Name="FirstName">Ted</Field>
          <Field Name="Title">Pattison</Field>
          <Field Name="WorkPhone">(813)813-8133</Field>
        </Row>
        <Row>
          <Field Name="FirstName">Mike</Field>
          <Field Name="Title">Morton</Field>
          <Field Name="WorkPhone">(800)BIG-TULS</Field>
        </Row>
      </Rows>
    </Data>

  </ListInstance>
</Elements>
